sharex/__init__.py
sharex/_version.py
sharex/api.py
sharex/cli.py
sharex/py.typed
sharex/utils.py
sharex_cli-0.0.3.dist-info/METADATA
sharex_cli-0.0.3.dist-info/WHEEL
sharex_cli-0.0.3.dist-info/entry_points.txt
sharex_cli-0.0.3.dist-info/licenses/LICENSE
sharex_cli-0.0.3.dist-info/RECORD
