Metadata-Version: 2.4
Name: sharex-cli
Version: 0.0.3
Summary: CLI to Upload Files to a ShareX Server using a ShareX Custom Uploader (.sxcu) Configuration File.
Project-URL: Changelog, https://github.com/cssnr/sharex-cli/releases
Project-URL: Discord, https://discord.gg/wXy6m2X8wY
Project-URL: Documentation, https://cssnr.github.io/sharex-cli/
Project-URL: Funding, https://ko-fi.com/cssnr
Project-URL: GitHub, https://github.com/cssnr/sharex-cli
Project-URL: Homepage, https://cssnr.com/
Project-URL: Issues, https://github.com/cssnr/sharex-cli/issues
Author: Shane
License: MIT License
License-File: LICENSE
Classifier: Natural Language :: English
Classifier: Operating System :: OS Independent
Classifier: Programming Language :: Python
Classifier: Programming Language :: Python :: 3
Classifier: Programming Language :: Python :: 3 :: Only
Classifier: Typing :: Typed
Requires-Python: >=3.10
Requires-Dist: jsonpath-ng<2,>=1
Requires-Dist: pyperclip<2,>=1
Requires-Dist: requests<3,>=2
Requires-Dist: typer>=0.20.0
